ttn/__init__.py
ttn/ttnmqtt.py
ttn-2.0.0.dist-info/DESCRIPTION.rst
ttn-2.0.0.dist-info/METADATA
ttn-2.0.0.dist-info/RECORD
ttn-2.0.0.dist-info/WHEEL
ttn-2.0.0.dist-info/metadata.json
ttn-2.0.0.dist-info/top_level.txt
ttnmqtt/__init__.py
ttnmqtt/ttnmqtt.py
