Metadata-Version: 2.0
Name: ttn
Version: 2.0.0
Summary: The Things Network Client
Home-page: https://github.com/TheThingsNetwork/python-app-sdk
Author: Emmanuelle Lejeail
Author-email: emmanuelle@thethingsindustries.com
License: MIT
Platform: UNKNOWN
Requires-Dist: paho-mqtt
Requires-Dist: events
Requires-Dist: grpcio
Requires-Dist: protobuf
Requires-Dist: google-api-python-client
Requires-Dist: google-cloud
